src/__init__.py
src/mixins.py
src/utils.py
django_image_compressor-0.3.1.dist-info/LICENSE
django_image_compressor-0.3.1.dist-info/METADATA
django_image_compressor-0.3.1.dist-info/WHEEL
django_image_compressor-0.3.1.dist-info/top_level.txt
django_image_compressor-0.3.1.dist-info/RECORD
