Metadata-Version: 2.1
Name: django-image-compressor
Version: 0.3.1
Summary: Image compressor for Django apps.
Home-page: https://github.com/yunusovbekir/django-image-compressor
Author: Bakir Yunusov
Author-email: yunusovbekir@gmail.com
License: MIT License
Download-URL: https://github.com/yunusovbekir/django-image-compressor
Keywords: django,image,compressor
Platform: UNKNOWN
Requires-Dist: Django (>=3.0)
Requires-Dist: Pillow (>=8.0)
